omicidx/__init__.py
omicidx/biosample.py
omicidx/geo/__init__.py
omicidx/geo/parser.py
omicidx/geo/pydantic_models.py
omicidx/ontologies/__init__.py
omicidx/ontologies/utils.py
omicidx/schema_tools.py
omicidx/scripts/__init__.py
omicidx/scripts/geo.py
omicidx/scripts/omicidx.py
omicidx/scripts/sra_entity_to_json.py
omicidx/sra/__init__.py
omicidx/sra/ebiutils.py
omicidx/sra/parser.py
omicidx/sra/pydantic_models.py
omicidx/utils.py
omicidx-1.17.0.dist-info/METADATA
omicidx-1.17.0.dist-info/WHEEL
omicidx-1.17.0.dist-info/entry_points.txt
omicidx-1.17.0.dist-info/RECORD
