Metadata-Version: 2.3
Name: omicidx
Version: 1.17.0
Summary: The OmicIDX project collects, reprocesses, and then republishes metadata from multiple public genomics repositories. Included are the NCBI SRA, Biosample, and GEO databases. Publication is via the cloud data warehouse platform Bigquery, a set of performant search and retrieval APIs, and a set of json-format files for easy incorporation into other projects.
License: MIT
Keywords: genomics,bioinformatics,open data,API
Author: Sean Davis
Author-email: seandavi@gmail.com
Requires-Python: >=3.9
Classifier: License :: OSI Approved :: MIT License
Classifier: Programming Language :: Python :: 3
Classifier: Programming Language :: Python :: 3.9
Classifier: Programming Language :: Python :: 3.10
Classifier: Programming Language :: Python :: 3.11
Classifier: Programming Language :: Python :: 3.12
Classifier: Programming Language :: Python :: 3.13
Requires-Dist: Click
Requires-Dist: aiohttp (>=3.6.2,<4.0.0)
Requires-Dist: biopython (>=1.81,<2.0)
Requires-Dist: httpx
Requires-Dist: orjson (>=3.9.2,<4.0.0)
Requires-Dist: pendulum
Requires-Dist: pronto (>=2.5.4,<3.0.0)
Requires-Dist: pydantic (>=2,<3)
Requires-Dist: pytest (>=7.4.0,<8.0.0)
Requires-Dist: requests (>=2.22,<3.0)
Requires-Dist: tenacity (>=8.0.1,<9.0.0)
Requires-Dist: trio (>=0.30.0,<0.31.0)
Requires-Dist: universal-pathlib
Project-URL: Repository, https://github.com/omicidx/omicidx-parsers
